LICENSE.txt
README.md
setup.cfg
setup.py
cerebstats/__init__.py
cerebstats.egg-info/PKG-INFO
cerebstats.egg-info/SOURCES.txt
cerebstats.egg-info/dependency_links.txt
cerebstats.egg-info/requires.txt
cerebstats.egg-info/top_level.txt
cerebstats/data_conditions/__init__.py
cerebstats/data_conditions/forHTmeans.py
cerebstats/data_conditions/forHTproportions.py
cerebstats/hypothesis_testings/__init__.py
cerebstats/hypothesis_testings/aboutmeans.py
cerebstats/hypothesis_testings/aboutmedians.py
cerebstats/hypothesis_testings/aboutproportions.py
cerebstats/stat_scores/__init__.py
cerebstats/stat_scores/chi2GOFScore.py
cerebstats/stat_scores/chi2GOFScore_test_with_datasets.py
cerebstats/stat_scores/chi2Score.py
cerebstats/stat_scores/chi2Score_test_with_datasets.py
cerebstats/stat_scores/fisherExactScore.py
cerebstats/stat_scores/fisherExactScore_test_with_datasets.py
cerebstats/stat_scores/mcNemarScore.py
cerebstats/stat_scores/mcNemarScore_test_with_datasets.py
cerebstats/stat_scores/tScore.py
cerebstats/stat_scores/zPropScore.py
cerebstats/stat_scores/zPropScore_test_with_datasets.py
cerebstats/stat_scores/zScore.py
cerebstats/stat_scores/zSignScore.py
cerebstats/stat_scores/zSignScore_test_with_datasets.py
cerebstats/stat_scores/zTwoSampleRankSumScore.py
cerebstats/stat_scores/zTwoSampleRankSumScore_test_with_datasets.py
cerebstats/stat_scores/zWilcoxSignedRankScore.py
cerebstats/stat_scores/zWilcoxSignedRankScore_test_with_datasets.py