Metadata-Version: 2.1
Name: cerebstats
Version: 0.0.3
Summary: Installable package 'cerebstats' for cerebunit
Home-page: https://github.com/cerebunit/cerebstats
Author: Lungsi
Author-email: lungsi.ngwua@cnrs.fr
License: BSD Clause-3 Revised
Download-URL: https://github.com/cerebunit/cerebstats/archive/refs/tags/v0.0.3.tar.gz
Keywords: VALIDATION,CEREBELLUM,NEUROSCIENCE,MODELING,SCIENTIFIC METHOD
Platform: UNKNOWN
Classifier: Development Status :: 3 - Alpha
Classifier: Intended Audience :: Developers
Classifier: License :: OSI Approved :: BSD License
Classifier: Programming Language :: Python :: 3.5
Classifier: Programming Language :: Python :: 3.6
Classifier: Programming Language :: Python :: 3.7
Classifier: Programming Language :: Python :: 3.8
License-File: LICENSE.txt
